tsp_c/__init__.py
tsp_c/_tsp_c.so
tsp_c/tsp_c.py
tsp_c-0.0.29.dist-info/LICENSE
tsp_c-0.0.29.dist-info/METADATA
tsp_c-0.0.29.dist-info/WHEEL
tsp_c-0.0.29.dist-info/top_level.txt
tsp_c-0.0.29.dist-info/RECORD
