Metadata-Version: 2.1
Name: tsp-c
Version: 0.0.29
Summary: A wrapper for c++ to solve the Traveling Salesman Problem
Home-page: https://github.com/kjudom/tsp-c
Author: Udom Janjarassuk
Author-email: kjudom@gmail.com
Project-URL: Bug Tracker, https://github.com/kjudom/tsp-c/issues
Classifier: Programming Language :: Python :: 3
Classifier: License :: OSI Approved :: MIT License
Classifier: Operating System :: OS Independent
Requires-Python: >=3.6
License-File: LICENSE
